sleep_utils/__init__.py
sleep_utils/gui.py
sleep_utils/plotting.py
sleep_utils/sigproc.py
sleep_utils/tools.py
sleep_utils/usleep_utils.py
sleep_utils-1.26.dist-info/METADATA
sleep_utils-1.26.dist-info/WHEEL
sleep_utils-1.26.dist-info/top_level.txt
sleep_utils-1.26.dist-info/RECORD
