Metadata-Version: 2.4
Name: sleep_utils
Version: 1.26
Summary: A collection of tools for sleep research
Home-page: http://github.com/skjerns/sleep-utils
Author: skjerns
Author-email: nomail@nomail.com
License: GNU 2.0
Classifier: Programming Language :: Python :: 3
Classifier: License :: OSI Approved :: MIT License
Classifier: Operating System :: OS Independent
Requires-Dist: appdirs
Requires-Dist: tqdm
Requires-Dist: mne
Requires-Dist: matplotlib
Requires-Dist: joblib
Requires-Dist: pandas
Requires-Dist: seaborn
Requires-Dist: scipy
Requires-Dist: lspopt
Requires-Dist: natsort
Requires-Dist: usleep-api
Dynamic: author
Dynamic: author-email
Dynamic: classifier
Dynamic: description
Dynamic: description-content-type
Dynamic: home-page
Dynamic: license
Dynamic: requires-dist
Dynamic: summary
